q1ss/__init__.py
q1ss/py.typed
q1ss/ap/__init__.py
q1ss/ap/base.py
q1ss/ap/explicit.py
q1ss/ap/generated.py
q1ss/ap/sequence.py
q1ss/ap/vectorized.py
q1ss/binalg/__init__.py
q1ss/binalg/affine.py
q1ss/binalg/base.py
q1ss/binalg/binmat.py
q1ss/binalg/binvec.py
q1ss/binalg/vectorized.py
q1ss/utils/__init__.py
q1ss/utils/options.py
q1ss-0.0.1.dist-info/LICENSE
q1ss-0.0.1.dist-info/METADATA
q1ss-0.0.1.dist-info/WHEEL
q1ss-0.0.1.dist-info/top_level.txt
q1ss-0.0.1.dist-info/RECORD
