Metadata-Version: 2.1
Name: q1ss
Version: 0.0.1
Summary: Quantum 1-Shot Signatures
Home-page: https://github.com/The-QSig-Commission/q1ss
Author: hashberg
Author-email: sg495@users.noreply.github.com
Project-URL: Bug Tracker, https://github.com/The-QSig-Commission/q1ss/issues
Classifier: Development Status :: 2 - Pre-Alpha
Classifier: Programming Language :: Python :: 3.12
Classifier: Programming Language :: Python :: 3.11
Classifier: Programming Language :: Python :: 3.10
Classifier: Operating System :: OS Independent
Classifier: Natural Language :: English
Classifier: Typing :: Typed
Requires-Python: >=3.10
License-File: LICENSE
Requires-Dist: typing-extensions >=4.6.0
Requires-Dist: typing-validation >=1.1.0
Requires-Dist: numpy >=1.26.1
Requires-Dist: optmanage >=1.1.1
Provides-Extra: dev
Requires-Dist: mypy ; extra == 'dev'
Requires-Dist: pytest ; extra == 'dev'
Requires-Dist: pytest-cov ; extra == 'dev'
